{
  "A Random Unique ID": "ARandomUniqueID",
  "AddressBook Email": "AddressBookEmail",
  "AddressBook First Name": "AddressBookFirstName",
  "AddressBook Last Name": "AddressBookLastName",
  "AddressBook Name": "AddressBookName",
  "AddressBook Nickname": "AddressBookNickname",
  "AddressBook Note": "AddressBookNote",
  "AddressBook Organization": "AddressBookOrganization",
  "All Audio Input Devices": "AllAudioInputDevices",
  "All Audio Output Devices": "AllAudioOutputDevices",
  "All Background Application Names": "AllBackgroundApplicationNames",
  "All Foreground Application Names": "AllForegroundApplicationNames",
  "All Running Application Names": "AllRunningApplicationNames",
  "All Screen Frames": "AllScreenFrames",
  "All Window Names": "AllWindowNames",
  "Calculation": "Calculation",
  "Calculation with Result in Binary": "CalculationWithResultInBinary",
  "Calculation with Result in Decimal": "CalculationWithResultInDecimal",
  "Calculation with Result in Hex": "CalculationWithResultInHex",
  "Calculation with Result in Octal": "CalculationWithResultInOctal",
  "Comma-separated list of the current execution instances": "CommaSeparatedListOfTheCurrentExecutionInstances",
  "Comma-separated list of variables accessed by this macro": "CommaSeparatedListOfVariablesAccessedByThisMacro",
  "Current Audio Input Device": "CurrentAudioInputDevice",
  "Current Audio Input Device UID": "CurrentAudioInputDeviceUID",
  "Current Audio Output Device": "CurrentAudioOutputDevice",
  "Current Audio Output Device UID": "CurrentAudioOutputDeviceUID",
  "Current Audio Sound Effects Device": "CurrentAudioSoundEffectsDevice",
  "Current Audio Sound Effects Device UID": "CurrentAudioSoundEffectsDeviceUID",
  "Current Mouse Location": "CurrentMouseLocation",
  "Current Track Album": "CurrentTrackAlbum",
  "Current Track Artist": "CurrentTrackArtist",
  "Current Track Name": "CurrentTrackName",
  "Current Track Rating": "CurrentTrackRating",
  "Delete (Hide a Variable)": "Delete",
  "Executing Macro": "ExecutingMacro",
  "Executing Macro Group": "ExecutingMacroGroup",
  "Executing Macro Group UUID": "ExecutingMacroGroupUUID",
  "Executing Macro UUID": "ExecutingMacroUUID",
  "Executing This Macro": "ExecutingThisMacro",
  "Executing This Macro Group": "ExecutingThisMacroGroup",
  "Executing This Macro Group UUID": "ExecutingThisMacroGroupUUID",
  "Executing This Macro UUID": "ExecutingThisMacroUUID",
  "Find Pasteboard": "FindPasteboard",
  "Finder Insertion Location Path": "FinderInsertionLocationPath",
  "First Screen Frame": "FirstScreenFrame",
  "Formatted (ICU) Date Time": "FormattedICUDateTime",
  "Formatted (ICU) Date Time For": "FormattedICUDateTimeFor",
  "Formatted (ICU) Date Time Minus": "FormattedICUDateTimeMinus",
  "Formatted (ICU) Date Time Plus": "FormattedICUDateTimePlus",
  "Formatted Calculation": "FormattedCalculation",
  "Front Application Bundle ID": "FrontApplicationBundleID",
  "Front Application Long Version": "FrontApplicationLongVersion",
  "Front Application Name": "FrontApplicationName",
  "Front Application Path": "FrontApplicationPath",
  "Front Application Version": "FrontApplicationVersion",
  "Front Browser Bundle ID": "FrontBrowserBundleID",
  "Front Browser Document Title": "FrontBrowserDocumentTitle",
  "Front Browser Document URL": "FrontBrowserDocumentURL",
  "Front Browser Field": "FrontBrowserField",
  "Front Browser JavaScript": "FrontBrowserJavaScript",
  "Front Browser Long Version": "FrontBrowserLongVersion",
  "Front Browser Name": "FrontBrowserName",
  "Front Browser Path": "FrontBrowserPath",
  "Front Browser Ready State": "FrontBrowserReadyState",
  "Front Browser Version": "FrontBrowserVersion",
  "Front Browser Window Name": "FrontBrowserWindowName",
  "Front Window Frame": "FrontWindowFrame",
  "Front Window Name": "FrontWindowName",
  "Front Window Position": "FrontWindowPosition",
  "Front Window Size": "FrontWindowSize",
  "Google Chrome Bundle ID": "GoogleChromeBundleID",
  "Google Chrome Document Title": "GoogleChromeDocumentTitle",
  "Google Chrome Document URL": "GoogleChromeDocumentURL",
  "Google Chrome Field": "GoogleChromeField",
  "Google Chrome JavaScript": "GoogleChromeJavaScript",
  "Google Chrome Long Version": "GoogleChromeLongVersion",
  "Google Chrome Name": "GoogleChromeName",
  "Google Chrome Path": "GoogleChromePath",
  "Google Chrome Ready State": "GoogleChromeReadyState",
  "Google Chrome Version": "GoogleChromeVersion",
  "Google Chrome Window Name": "GoogleChromeWindowName",
  "ID of Last Keyboard Maestro Engine Window Opened by This Macro": "IDOfLastKeyboardMaestroEngineWindowOpenedByThisMacro",
  "ID of the Last Aborted Action": "IDOfTheLastAbortedAction",
  "JSON From Dictionary": "JSONFromDictionary",
  "JSON From Variables": "JSONFromVariables",
  "JSON Value": "JSONValue",
  "Keyboard Layout Input Source": "KeyboardLayoutInputSource",
  "Keyboard Maestro Long Version": "KeyboardMaestroLongVersion",
  "Keyboard Maestro Version": "KeyboardMaestroVersion",
  "Linefeed (\\n)": "Linefeed",
  "Long Date": "LongDate",
  "Machine IP Address": "MachineIPAddress",
  "Machine Name": "MachineName",
  "Machine Unique ID": "MachineUniqueID",
  "Macro Name for UUID": "MacroNameForUUID",
  "Mail BCC Recipients": "MailBCCRecipients",
  "Mail CC Recipients": "MailCCRecipients",
  "Mail Contents": "MailContents",
  "Mail Raw Source": "MailRawSource",
  "Mail Recipients": "MailRecipients",
  "Mail Reply To": "MailReplyTo",
  "Mail Sender": "MailSender",
  "Mail Subject": "MailSubject",
  "Mail To Recipients": "MailToRecipients",
  "Main Screen Frame": "MainScreenFrame",
  "Main Screen Possible Resolutions (array of resolutions)": "MainScreenPossibleResolutions",
  "Main Screen Resolution (width,height,pixelwidth,pixelheight,refresh)": "MainScreenResolution",
  "Main Screen Visible Frame": "MainScreenVisibleFrame",
  "Music Player State (stopped/playing/paused/fast forwarding/rewinding/not running)": "MusicPlayerState",
  "Named Clipboard": "NamedClipboard",
  "Named Clipboard Flavors": "NamedClipboardFlavors",
  "Network Location": "NetworkLocation",
  "Number Date": "NumberDate",
  "Opaque ID of the Current Execution Instance": "OpaqueIDOfTheCurrentExecutionInstance",
  "Option-Return (Insert Text by Typing Only)": "OptionReturn",
  "Past Clipboard": "PastClipboard",
  "Past Clipboard Flavors": "PastClipboardFlavors",
  "Position Cursor (Insert Text Only)": "PositionCursor",
  "Previous Application Name": "PreviousApplicationName",
  "Prompt for Snippet Placeholder (Default from Variable)": "PromptForSnippetPlaceholderDefaultFromVariable",
  "Prompt for Snippet Placeholder (Default Text)": "PromptForSnippetPlaceholderDefaultText",
  "Return (\\r)": "Return",
  "Safari Bundle ID": "SafariBundleID",
  "Safari Document Title": "SafariDocumentTitle",
  "Safari Document URL": "SafariDocumentURL",
  "Safari Field": "SafariField",
  "Safari JavaScript": "SafariJavaScript",
  "Safari Long Version": "SafariLongVersion",
  "Safari Name": "SafariName",
  "Safari Path": "SafariPath",
  "Safari Ready State": "SafariReadyState",
  "Safari Version": "SafariVersion",
  "Safari Window Name": "SafariWindowName",
  "Second Screen Frame": "SecondScreenFrame",
  "Short Date": "ShortDate",
  "Space": "Space",
  "Success Result of Last Action": "SuccessResultOfLastAction",
  "System Clipboard": "SystemClipboard",
  "System Clipboard Flavors": "SystemClipboardFlavors",
  "System Long Version": "SystemLongVersion",
  "System Version": "SystemVersion",
  "System Volume": "SystemVolume",
  "Tab (\\t)": "Tab",
  "The Last Alert Button Selected": "TheLastAlertButtonSelected",
  "The Last Custom HTML Result": "TheLastCustomHTMLResult",
  "The Last Found Image": "TheLastFoundImage",
  "The Last Prompt Button Selected": "TheLastPromptButtonSelected",
  "The Macro Name of the Specified Instance": "TheMacroNameOfTheSpecifiedInstance",
  "The Modifiers Used When Completing a Prompt With List Action": "TheModifiersUsedWhenCompletingAPromptWithListAction",
  "The Path of the Front Window’s Document": "ThePathOfTheFrontWindowDocument",
  "The Path of the Selected Finder Item": "ThePathOfTheSelectedFinderItem",
  "The Paths of the Selected Finder Items": "ThePathsOfTheSelectedFinderItems",
  "The Text Entered in a Paste by Name Action": "TheTextEnteredInAPasteByNameAction",
  "The Text Entered in a Prompt With List Action": "TheTextEnteredInAPromptWithListAction",
  "The Text Entered in a Select Menu by Name Action": "TheTextEnteredInASelectMenuByNameAction",
  "Time": "Time",
  "Time With Seconds": "TimeWithSeconds",
  "Tripped Trigger Clipboard Flavors": "TrippedTriggerClipboardFlavors",
  "Tripped Trigger Clipboard Value": "TrippedTriggerClipboardValue",
  "Tripped Trigger Text": "TrippedTriggerText",
  "Tripped Trigger Type": "TrippedTriggerType",
  "Tripped Trigger Value": "TrippedTriggerValue",
  "User Home Directory": "UserHomeDirectory",
  "User Login ID": "UserLoginID",
  "User Name": "UserName",
  "Wireless Network Name(s)": "WirelessNetworkNames"
}